{"d":{"114":{"i":"7Kk83KSdI044UbqrtYmQII","is":"USUM71601114","n":"Rocket Ship","a":[{"i":"4yiQZ8tQPux8cPriYMWUFP","n":"Gwen Stefani"}],"p":32,"r":"2016-03-18","l":"Interscope","im":"https://i.scdn.co/image/ab67616d0000b27351bc6da4a50cc5a04ee613d9","ps":[{"i":"37i9dQZF1EFQn0XRhyzu2L","n":229,"a":1614608671000,"p":8}],"pp":8},"115":{"i":"0lvCgY0ZDo6krZgqIxYLHb","is":"USUM71601115","n":"Getting Warmer","a":[{"i":"4yiQZ8tQPux8cPriYMWUFP","n":"Gwen Stefani"}],"p":33,"r":"2016-03-18","l":"Interscope","im":"https://i.scdn.co/image/ab67616d0000b27351bc6da4a50cc5a04ee613d9","ps":[{"i":"37i9dQZF1EFQn0XRhyzu2L","n":215,"a":1614608671000,"p":9}],"pp":9},"116":{"i":"11fdGwNzgw5bR203OcGE07","is":"USUM71601116","n":"Obsessed","a":[{"i":"4yiQZ8tQPux8cPriYMWUFP","n":"Gwen Stefani"}],"p":32,"r":"2016-03-18","l":"Interscope","im":"https://i.scdn.co/image/ab67616d0000b27351bc6da4a50cc5a04ee613d9","ps":[{"i":"37i9dQZF1EFQn0XRhyzu2L","n":228,"a":1614608671000,"p":8}],"pp":8},"117":{"i":"0uce96UnSAGDTyle6gUwtk","is":"USUM71601117","n":"Splash","a":[{"i":"4yiQZ8tQPux8cPriYMWUFP","n":"Gwen Stefani"}],"p":30,"r":"2016-03-18","l":"Interscope","im":"https://i.scdn.co/image/ab67616d0000b27351bc6da4a50cc5a04ee613d9","ps":[{"i":"37i9dQZF1EFQn0XRhyzu2L","n":232,"a":1614608671000,"p":8}],"pp":8},"168":{"i":"1n8ZUpQ0iVY6gVBgEUdA2Q","is":"USUM71601168","n":"Rock Bottom","a":[{"i":"5p7f24Rk5HkUZsaS3BLG5F","n":"Hailee Steinfeld"},{"i":"6T5tfhQCknKG4UnH90qGnz","n":"DNCE"}],"p":36,"r":"2016-08-19","l":"Universal Records","im":"https://i.scdn.co/image/ab67616d0000b273eb66f3b0973057df6de26a08","ps":[{"i":"37i9dQZF1DX0KGZxcPEEqa","n":19,"a":1611841585000,"p":178},{"i":"37i9dQZF1EFQn0XRhyzu2L","n":21,"a":1614608670000,"p":64}],"pp":242},"293":{"i":"23WI5V2eD4EyGKxSl7Pyeq","is":"USUM71601293","n":"Andas En Mi Cabeza","a":[{"i":"5NS0854TqZQVoRmJKSWtFZ","n":"Chino & Nacho"},{"i":"4VMYDCV2IEDYJArk749S6m","n":"Daddy Yankee"}],"p":72,"r":"2016-02-19","l":"UMLE - Machete","im":"https://i.scdn.co/image/ab67616d0000b2736df5cc472d61a635abab06cf","ps":[{"i":"37i9dQZF1DX9H3lqBKp7yC","n":81,"a":1611062120000,"p":209},{"i":"37i9dQZF1DX7alvT6zKWrM","n":94,"a":1611142644000,"p":176},{"i":"37i9dQZF1DXbhNh5DYTmwV","n":4,"a":1614315660000,"p":122},{"i":"37i9dQZF1DX2EiUAL7Wdfc","n":60,"a":1614098326000,"p":104}],"pp":611},"375":{"i":"6WKk8l8EXiwPBYlmSlhZWx","is":"USUM71601375","n":"Therapy Session","a":[{"i":"6fOMl44jA4Sp5b9PpYCkzz","n":"NF"}],"p":66,"r":"2016-04-22","l":"Capitol CMG Label Group","im":"https://i.scdn.co/image/ab67616d0000b27314c95b3975386061f46f3983","ps":[{"i":"37i9dQZF1DX1xEPBKyoFUz","n":4,"a":1611320400000,"p":299}],"pp":299},"616":{"i":"4HdxI4yrlmN2C9GaMD9mxL","is":"USUM71601616","n":"Cowboy Hat","a":[{"i":"4MoAOfV4ROWofLG3a3hhBN","n":"Jon Pardi"}],"p":52,"r":"2016-05-13","l":"Capitol Records Nashville","im":"https://i.scdn.co/image/ab67616d0000b27314d09c1ad67f2028764ee0f4","ps":[{"i":"37i9dQZF1DWXi7h4mmmkzD","n":74,"a":1612374666000,"p":338}],"pp":338},"617":{"i":"0bPnT6i9H1p8Vd85GS6Z7I","is":"USUM71601617","n":"Night Shift","a":[{"i":"4MoAOfV4ROWofLG3a3hhBN","n":"Jon Pardi"}],"p":70,"r":"2016-05-13","l":"Capitol Records Nashville","im":"https://i.scdn.co/image/ab67616d0000b27314d09c1ad67f2028764ee0f4","ps":[{"i":"37i9dQZF1DXdgnLr18vPvu","n":50,"a":1612367823000,"p":541},{"i":"37i9dQZF1DWXi7h4mmmkzD","n":35,"a":1612374666000,"p":500},{"i":"37i9dQZF1DXdfhOsjRMISB","n":12,"a":1614708060000,"p":449},{"i":"37i9dQZF1DX3ph0alWhOXm","n":43,"a":1612374760000,"p":224},{"i":"37i9dQZF1DX5OrO2Jxuvdn","n":15,"a":1612368949000,"p":144}],"pp":1858},"619":{"i":"7f08qp3HROTkfrtNpiYGGo","is":"USUM71601619","n":"Dirt On My Boots","a":[{"i":"4MoAOfV4ROWofLG3a3hhBN","n":"Jon Pardi"}],"p":70,"r":"2016-05-13","l":"Capitol Records Nashville","im":"https://i.scdn.co/image/ab67616d0000b27314d09c1ad67f2028764ee0f4","ps":[{"i":"37i9dQZF1DXdgnLr18vPvu","n":10,"a":1612367823000,"p":809},{"i":"37i9dQZF1DXbIbVYph0Zr5","n":33,"a":1612374595000,"p":332},{"i":"37i9dQZF1DWXi7h4mmmkzD","n":80,"a":1612374666000,"p":318}],"pp":1459},"623":{"i":"0w3Q14i073jLoew1hgJkwD","is":"USUM71601623","n":"Heartache On The Dance Floor","a":[{"i":"4MoAOfV4ROWofLG3a3hhBN","n":"Jon Pardi"}],"p":70,"r":"2016-05-13","l":"Capitol Records Nashville","im":"https://i.scdn.co/image/ab67616d0000b27314d09c1ad67f2028764ee0f4","ps":[{"i":"37i9dQZF1DWYnwbYQ5HnZU","n":22,"a":1614574920000,"p":1014},{"i":"37i9dQZF1DXdgnLr18vPvu","n":19,"a":1612367823000,"p":739},{"i":"37i9dQZF1DWXi7h4mmmkzD","n":13,"a":1612374666000,"p":623},{"i":"37i9dQZF1DX3ph0alWhOXm","n":55,"a":1612374760000,"p":199},{"i":"37i9dQZF1DX5OrO2Jxuvdn","n":68,"a":1612368949000,"p":85}],"pp":2660},"673":{"i":"2fgAJeky8Cpsr8Cfvn2NVp","is":"USUM71601673","n":"untitled 03 | 05.28.2013.","a":[{"i":"2YZyLoL8N0Wb9xBt1NhZWg","n":"Kendrick Lamar"}],"p":52,"r":"2016-03-04","l":"Aftermath III JV","im":"https://i.scdn.co/image/ab67616d0000b2738c697f553a46006a5d8886b2","ps":[{"i":"37i9dQZF1DWSic3nMj9lmy","n":187,"a":1613929677000,"p":10}],"pp":10},"797":{"i":"6TOfPHF57Qhlbfm5lhZ9k1","is":"USUM71601797","n":"Be Alright","a":[{"i":"66CXWjxzNUsdJxJ2JdwvnR","n":"Ariana Grande"}],"p":56,"r":"2016-04-01","l":"Universal Records","im":"https://i.scdn.co/image/ab67616d0000b27333342c57a9b2c4e04c97b3f5","ps":[{"i":"37i9dQZF1EFNsJgooxLfdP","n":6,"a":1614608677000,"p":66}],"pp":66},"826":{"i":"2h1IPjP471JJRSShTHRUhi","is":"USUM71601826","n":"Dangerous Woman","a":[{"i":"66CXWjxzNUsdJxJ2JdwvnR","n":"Ariana Grande"}],"p":0,"r":"2016-05-20","l":"Universal Music Group","im":"https://i.scdn.co/image/ab67616d0000b2737227f5854239a059af211d5b","ps":[{"i":"37i9dQZF1DX0KGZxcPEEqa","n":28,"a":1611841585000,"p":163}],"pp":163},"827":{"i":"2meEiZKWkiN28gITzFwQo5","is":"USUM71601827","n":"Into You","a":[{"i":"66CXWjxzNUsdJxJ2JdwvnR","n":"Ariana Grande"}],"p":75,"r":"2016-05-20","l":"Universal Records","im":"https://i.scdn.co/image/ab67616d0000b2735f9393fda71e7df39b34defd","ps":[{"i":"37i9dQZF1DX5Ejj0EkURtP","n":103,"a":1613372199000,"p":825},{"i":"37i9dQZF1DXckSQXNNdGD6","n":43,"a":1614294120000,"p":58}],"pp":883},"828":{"i":"59NC8SuXPiSaiYL69XQ4dt","is":"USUM71601828","n":"Let Me Love You","a":[{"i":"66CXWjxzNUsdJxJ2JdwvnR","n":"Ariana Grande"},{"i":"55Aa2cqylxrFIXC767Z865","n":"Lil Wayne"}],"p":59,"r":"2016-04-01","l":"Universal Records","im":"https://i.scdn.co/image/ab67616d0000b27333342c57a9b2c4e04c97b3f5","ps":[{"i":"37i9dQZF1EFNsJgooxLfdP","n":7,"a":1614608677000,"p":66}],"pp":66},"094":{"i":"275a9yzwGB6ncAW4SxY7q3","is":"USUM71601094","n":"Panda","a":[{"i":"7pFeBzX627ff0VnN6bxPR4","n":"Desiigner"}],"p":67,"r":"2016-02-26","l":"Getting Out Our Dreams Inc. (G.O.O.D.) Music / IDJ","im":"https://i.scdn.co/image/ab67616d0000b273584ad36d1712bc9d51e797ff","ps":[{"i":"37i9dQZF1DWUVpAXiEPK8P","n":41,"a":1614597963000,"p":1252},{"i":"37i9dQZF1DX3ORvAIr1RbU","n":25,"a":1614301587000,"p":152},{"i":"37i9dQZF1DWSRbZUjHUFIA","n":35,"a":1614309257000,"p":128},{"i":"2NoR0KhNZ8oZnC3HoNt2FV","n":524,"a":1516388086000,"p":2}],"pp":1534},"082":{"i":"7AjveaJTT8WQn5UTEgvH1E","is":"USUM71601082","n":"Misery","a":[{"i":"4yiQZ8tQPux8cPriYMWUFP","n":"Gwen Stefani"}],"p":38,"r":"2016-03-18","l":"Interscope","im":"https://i.scdn.co/image/ab67616d0000b273207babffed2c37e43256bd15","ps":[{"i":"37i9dQZF1EFQn0XRhyzu2L","n":111,"a":1614608671000,"p":26}],"pp":26},"016":{"i":"42MC4Kh9LtGCUnjfUyY6S2","is":"USUM71601016","n":"Asking 4 It","a":[{"i":"4yiQZ8tQPux8cPriYMWUFP","n":"Gwen Stefani"},{"i":"6PXS4YHDkKvl1wkIl4V8DL","n":"Fetty Wap"}],"p":30,"r":"2016-03-18","l":"Interscope","im":"https://i.scdn.co/image/ab67616d0000b273207babffed2c37e43256bd15","ps":[{"i":"37i9dQZF1EFQn0XRhyzu2L","n":136,"a":1614608671000,"p":20}],"pp":20},"006":{"i":"5Rb2UR9gKQ0FaySYbsr4Xy","is":"USUM71601006","n":"Send Me A Picture","a":[{"i":"4yiQZ8tQPux8cPriYMWUFP","n":"Gwen Stefani"}],"p":28,"r":"2016-03-18","l":"Interscope","im":"https://i.scdn.co/image/ab67616d0000b273207babffed2c37e43256bd15","ps":[{"i":"37i9dQZF1EFQn0XRhyzu2L","n":159,"a":1614608671000,"p":16}],"pp":16},"003":{"i":"5aB3hpEAE1hDSQ2wZdrtsi","is":"USUM71601003","n":"Truth","a":[{"i":"4yiQZ8tQPux8cPriYMWUFP","n":"Gwen Stefani"}],"p":26,"r":"2016-03-18","l":"Interscope","im":"https://i.scdn.co/image/ab67616d0000b273207babffed2c37e43256bd15","ps":[{"i":"37i9dQZF1EFQn0XRhyzu2L","n":167,"a":1614608671000,"p":15}],"pp":15},"004":{"i":"02XUnEfZexXh9bj66FeK4Y","is":"USUM71601004","n":"Me Without You","a":[{"i":"4yiQZ8tQPux8cPriYMWUFP","n":"Gwen Stefani"}],"p":23,"r":"2016-03-18","l":"Interscope","im":"https://i.scdn.co/image/ab67616d0000b273207babffed2c37e43256bd15","ps":[{"i":"37i9dQZF1EFQn0XRhyzu2L","n":188,"a":1614608671000,"p":12}],"pp":12},"007":{"i":"0ETxZFWAUN1RVuRUzSFHCn","is":"USUM71601007","n":"Red Flag","a":[{"i":"4yiQZ8tQPux8cPriYMWUFP","n":"Gwen Stefani"}],"p":20,"r":"2016-03-18","l":"Interscope","im":"https://i.scdn.co/image/ab67616d0000b273207babffed2c37e43256bd15","ps":[{"i":"37i9dQZF1EFQn0XRhyzu2L","n":195,"a":1614608671000,"p":11}],"pp":11},"023":{"i":"6Nqw5ZZASs98p7e4zfIIqM","is":"USUM71601023","n":"Loveable","a":[{"i":"4yiQZ8tQPux8cPriYMWUFP","n":"Gwen Stefani"}],"p":20,"r":"2016-03-18","l":"Interscope","im":"https://i.scdn.co/image/ab67616d0000b273207babffed2c37e43256bd15","ps":[{"i":"37i9dQZF1EFQn0XRhyzu2L","n":223,"a":1614608671000,"p":8}],"pp":8}},"s":[]}