{"d":{"im1815482":{"i":"0FkuwRl4CrK46O517nw02k","is":"KRMIM1815482","n":"First Snow 첫눈 오는 날에는","a":[{"i":"5L1KLMHjZsAtmQFuRmkU0O","n":"Jerry.K"}],"p":0,"r":"2018-12-30","l":"DAZE ALIVE","im":"https://i.scdn.co/image/ab67616d0000b2732011708539464680e2aafec0","ps":[{"i":"6YDckiQHBPbMvpcNWsWLRk","n":115,"a":1572874166000,"p":25}],"pp":25},"im1811191":{"i":"6QZJTunvjAU44kpXzDNXzn","is":"KRMIM1811191","n":"Hold Me Like It’s Forever","a":[{"i":"4ht1mwP4ouSu79jOOktCY3","n":"Fromm"},{"i":"7c1HgFDe8ogy5NOZ1ANCJQ","n":"Car, the garden"}],"p":39,"r":"2018-11-06","l":"Maxine","im":"https://i.scdn.co/image/ab67616d0000b273726d534ee21640d3f00e8daa","ps":[{"i":"37i9dQZF1DWZYjbSZYSpu6","n":39,"a":1614650424000,"p":369},{"i":"37i9dQZF1DX2SFBzpAPi7n","n":38,"a":1614596598000,"p":184}],"pp":553},"im1815674":{"i":"183LBqwbF66GTjGMH7fiMP","is":"KRMIM1815674","n":"Pretend","a":[{"i":"3j0Q7sspsBVQm6SdlkqYp1","n":"Lee Aram"}],"p":25,"r":"2019-01-03","l":"WM Korea","im":"https://i.scdn.co/image/ab67616d0000b2734d790684c497c90877fc2656","ps":[{"i":"37i9dQZF1DX6Cy4Vr7Hu2y","n":1,"a":1614652106000,"p":656}],"pp":656},"im1815150":{"i":"0xq4ZTcmwBfkPGo4RRKmMe","is":"KRMIM1815150","n":"Gotta Go","a":[{"i":"2PSJ6YriU7JsFucxACpU7Y","n":"CHUNG HA"}],"p":66,"r":"2019-01-02","l":"Genie Music Corporation, Stone Music Entertainment","im":"https://i.scdn.co/image/ab67616d0000b2733de8d21c10a5beed844bba5b","ps":[{"i":"37i9dQZF1DX6Cy4Vr7Hu2y","n":22,"a":1614652106000,"p":531},{"i":"37i9dQZF1DX5eq3AONkaho","n":134,"a":1614677339000,"p":72}],"pp":603},"im1814378":{"i":"1h2zAA8piBm3LSUz9HK9D8","is":"KRMIM1814378","n":"To All 서른에게","a":[{"i":"4GAVUIrGNz35VbCFfHTsca","n":"saevom"},{"i":"3jMgodiEy9ze7ksHxPkc9v","n":"Jeon So Hyun"}],"p":4,"r":"2018-12-09","l":"unsvrecords","im":"https://i.scdn.co/image/ab67616d0000b27382e711c36096ba6cfdcfa166","ps":[{"i":"37i9dQZF1DX6Cy4Vr7Hu2y","n":25,"a":1614652106000,"p":515}],"pp":515},"im1810057":{"i":"5RvuwSjuIkAiqviPuGWWgE","is":"KRMIM1810057","n":"Wisue 햇빛처럼 빼어난","a":[{"i":"6AtePm872YnH0PPQZpNFry","n":"WISUE"}],"p":12,"r":"2018-10-13","l":"Acoustie Music","im":"https://i.scdn.co/image/ab67616d0000b2734463ae4f7c1d062eba59c988","ps":[{"i":"37i9dQZF1DX6Cy4Vr7Hu2y","n":31,"a":1614652106000,"p":485}],"pp":485},"im1814767":{"i":"1i1ucbKohSxZicBdhI46I3","is":"KRMIM1814767","n":"Bleu","a":[{"i":"32QKRIXj5Cfn0PDxlM90Cn","n":"seoninjang 선인장"}],"p":0,"r":"2018-12-26","l":"seoninjang","im":"https://i.scdn.co/image/ab67616d0000b273039c4535b1522a970b6baf4e","ps":[{"i":"37i9dQZF1DX6Cy4Vr7Hu2y","n":38,"a":1614652106000,"p":452}],"pp":452},"im1814418":{"i":"5rMA9ymHfXJLIfWYSSURC3","is":"KRMIM1814418","n":"Old Carousel","a":[{"i":"62i8ukH7NagOk7lZE6B3xA","n":"yourbeagle"}],"p":17,"r":"2019-01-06","l":"WM Korea","im":"https://i.scdn.co/image/ab67616d0000b2732bc3f7c07f26a5c9c56fd75e","ps":[{"i":"37i9dQZF1DX6Cy4Vr7Hu2y","n":44,"a":1614652106000,"p":426},{"i":"37i9dQZF1DX1uG5byNIgDA","n":49,"a":1614576346000,"p":275}],"pp":701},"im1814254":{"i":"13TsBlKDFHcBrxCzAZv3qy","is":"KRMIM1814254","n":"How Do You Feel 어떨 것 같아","a":[{"i":"6ay9YyFyAgf6eORHdLKKDf","n":"HAIL"}],"p":14,"r":"2018-12-11","l":"What's The Weather","im":"https://i.scdn.co/image/ab67616d0000b273c3335bdb6fb945b5c5713ddb","ps":[{"i":"37i9dQZF1DX6Cy4Vr7Hu2y","n":45,"a":1614652106000,"p":421}],"pp":421},"im1805020":{"i":"4x5l1gjNcoBhhWBPEMo7OQ","is":"KRMIM1805020","n":"Love U","a":[{"i":"2PSJ6YriU7JsFucxACpU7Y","n":"CHUNG HA"}],"p":51,"r":"2018-07-18","l":"Stone Music Entertainment","im":"https://i.scdn.co/image/ab67616d0000b2738442904eb91ddcbb48e581bb","ps":[{"i":"37i9dQZF1DX6Cy4Vr7Hu2y","n":61,"a":1614652106000,"p":359},{"i":"37i9dQZF1DX1lU51fgoMhF","n":26,"a":1614655148000,"p":224}],"pp":583},"im1805227":{"i":"481yYUbtfs67PaKYKxJOeF","is":"KRMIM1805227","n":"SEE SEA","a":[{"i":"78sJswwVn4P8aEhkF4K6fQ","n":"Hyolyn"}],"p":31,"r":"2018-07-20","l":"㈜ 브리지","im":"https://i.scdn.co/image/ab67616d0000b2733f14bcb9597f71bcc77381b6","ps":[{"i":"37i9dQZF1DX5eq3AONkaho","n":7,"a":1614677339000,"p":259},{"i":"37i9dQZF1DX1lU51fgoMhF","n":56,"a":1614655148000,"p":166},{"i":"37i9dQZF1DX1lU51fgoMhF","n":64,"a":1614655148000,"p":153}],"pp":578},"im1804477":{"i":"76QwAlBSjI9a08bqlQL92c","is":"KRMIM1804477","n":"FLOWER","a":[{"i":"3T49KbzLgtqWEUhrP8XUJZ","n":"Varsity"}],"p":25,"r":"2018-07-09","l":"Stone Music Entertainment","im":"https://i.scdn.co/image/ab67616d0000b27393d95bd18d0365dd3871c94b","ps":[{"i":"37i9dQZF1DX5eq3AONkaho","n":85,"a":1614677339000,"p":118}],"pp":118},"im1809772":{"i":"1GRcZ66VWTuCWHfENuebh9","is":"KRMIM1809772","n":"Alchemy","a":[{"i":"3MnicHyslW5NAnIMcOsGeK","n":"Damian"}],"p":18,"r":"2018-10-09","l":"Stone Music Entertainment","im":"https://i.scdn.co/image/ab67616d0000b273059dd7684f5f0b80b0ceb528","ps":[{"i":"37i9dQZF1DX82qPOvdCxxq","n":9,"a":1613118929000,"p":118}],"pp":118},"im1814419":{"i":"7c2QRRGd0J20G57dMjzKW5","is":"KRMIM1814419","n":"Dream (feat. IndEgo Aid)","a":[{"i":"62i8ukH7NagOk7lZE6B3xA","n":"yourbeagle"},{"i":"5qGemt8SgMneJacS62LXRA","n":"IndEgo Aid"}],"p":19,"r":"2019-01-06","l":"WM Korea","im":"https://i.scdn.co/image/ab67616d0000b2732bc3f7c07f26a5c9c56fd75e","ps":[{"i":"37i9dQZF1DXdR77H5Z8MIM","n":43,"a":1614161685000,"p":222}],"pp":222},"im1811882":{"i":"7nbJ3glHErMd2tcDbTYvrU","is":"KRMIM1811882","n":"Be Happy","a":[{"i":"62i8ukH7NagOk7lZE6B3xA","n":"yourbeagle"}],"p":21,"r":"2018-11-11","l":"WM Korea","im":"https://i.scdn.co/image/ab67616d0000b2730aece531ab90563cc76fff7e","ps":[{"i":"37i9dQZF1DX1uG5byNIgDA","n":10,"a":1614576346000,"p":407}],"pp":407},"im1807343":{"i":"0G94mkN5scLEgD8iVvxeDc","is":"KRMIM1807343","n":"Jazz In My","a":[{"i":"4ZPInhlYlpaCsk1vnHmKBP","n":"Samuel Seo"}],"p":0,"r":"2018-09-12","l":"Stone Music Entertainment","im":"https://i.scdn.co/image/ab67616d0000b27380bac01341568e33042a5848","ps":[{"i":"37i9dQZF1DX1uG5byNIgDA","n":42,"a":1614576346000,"p":295}],"pp":295},"im1807703":{"i":"3WJLkdcrx8IFtftV3q0Zh5","is":"KRMIM1807703","n":"MRJM","a":[{"i":"3uo7KLyxuiANGmwDocxMnw","n":"Nieah"},{"i":"2HdW2ZlTwYhsFnZU0nilCv","n":"Paul"}],"p":30,"r":"2018-09-07","l":"Stone Music Entertainment","im":"https://i.scdn.co/image/ab67616d0000b27350de5719e03ed97acfec9edb","ps":[{"i":"37i9dQZF1DX5g856aiKiDS","n":19,"a":1614649797000,"p":441}],"pp":441},"im1800522":{"i":"3aQgPv1KBomvz5hQbKgkvS","is":"KRMIM1800522","n":"Luv Highway","a":[{"i":"48BSHaU3lXnM3pYHyeqLXN","n":"Eyedi"}],"p":10,"r":"2018-05-16","l":"베이스캠프스튜디오","im":"https://i.scdn.co/image/ab67616d0000b273443ba6755d207f6866d8d3dd","ps":[{"i":"37i9dQZF1DX5g856aiKiDS","n":33,"a":1614649797000,"p":383}],"pp":383},"im1803084":{"i":"7zRNdEsHWADTxFF1RkN3Vg","is":"KRMIM1803084","n":"Endless night","a":[{"i":"4VsMli3t4LtmPPGCHcyfON","n":"Red House"}],"p":28,"r":"2018-06-19","l":"Stone Music Entertainment","im":"https://i.scdn.co/image/ab67616d0000b2739979659b8df166e1b0e25ff7","ps":[{"i":"37i9dQZF1DX5g856aiKiDS","n":41,"a":1614649797000,"p":354}],"pp":354},"im1813197":{"i":"41mmblVBKV1QqzAsaq9ogD","is":"KRMIM1813197","n":"When It Snows 눈이 오는 날","a":[{"i":"5UT1mOF7JAjcc7e3wen8vw","n":"We Are The Night"}],"p":8,"r":"2018-12-02","l":"big.wav Music","im":"https://i.scdn.co/image/ab67616d0000b2734d68f506d555cec8e044467f","ps":[{"i":"37i9dQZF1DXdTb8AG95jne","n":15,"a":1614650283000,"p":448}],"pp":448},"im1808720":{"i":"2WH59CCJ7KMVRIRyG7za66","is":"KRMIM1808720","n":"To Him","a":[{"i":"1KsLHf4SObKZZUWrENllYL","n":"e_so"}],"p":15,"r":"2018-09-17","l":"e_so","im":"https://i.scdn.co/image/ab67616d0000b273383c59083b94a028d1a53537","ps":[{"i":"37i9dQZF1DXdTb8AG95jne","n":26,"a":1614650283000,"p":401}],"pp":401},"im1806342":{"i":"2LzB2eVxvivryMZrWWdtOQ","is":"KRMIM1806342","n":"Bonjour","a":[{"i":"4Lz3x0VAxs0qbTSrlDN1xa","n":"PAIIEK"},{"i":"0eJlkBWrxb681CK9vtvwxV","n":"Hyun-Ah Park"}],"p":0,"r":"2018-08-14","l":"BLANC CONNEXION","im":"https://i.scdn.co/image/ab67616d0000b2731882b0a54fadeabc0b7bfc24","ps":[{"i":"37i9dQZF1DXdTb8AG95jne","n":31,"a":1614650283000,"p":381}],"pp":381},"im1812570":{"i":"1YJ5G3mdv6Bps9XhbIv89E","is":"KRMIM1812570","n":"Red Lines","a":[{"i":"4Lxb5bo6TR7l8QL8UxDdd6","n":"Pony"},{"i":"4ht1mwP4ouSu79jOOktCY3","n":"Fromm"}],"p":0,"r":"2018-11-07","l":"Pony","im":"https://i.scdn.co/image/ab67616d0000b2731a69bd4c9901ae760dae8431","ps":[{"i":"37i9dQZF1DXdTb8AG95jne","n":32,"a":1614650283000,"p":378}],"pp":378},"im1802204":{"i":"2S1Y3QDbYtkkOx2Vahgv56","is":"KRMIM1802204","n":"Somethink","a":[{"i":"4HkkHrzTl7HzsehSCzc3Tf","n":"The Colored Paper"}],"p":19,"r":"2018-06-23","l":"NoiseSymphony","im":"https://i.scdn.co/image/ab67616d0000b273f982686b3552ef71a01aa546","ps":[{"i":"37i9dQZF1DXdTb8AG95jne","n":38,"a":1614650283000,"p":356}],"pp":356},"im1812934":{"i":"4zvIT9fIJxLXZc5RDMuYZR","is":"KRMIM1812934","n":"O`Chunnki","a":[{"i":"2sCSfdtkRpjNWt2O2GabKA","n":"Mono. J"}],"p":3,"r":"2018-11-20","l":"Mono. J Music","im":"https://i.scdn.co/image/ab67616d0000b273be15416d653a2efc90d7a63d","ps":[{"i":"37i9dQZF1DXdTb8AG95jne","n":41,"a":1614650283000,"p":345}],"pp":345},"im1805982":{"i":"25CZZwDOl3w7Wm7TeYI6vt","is":"KRMIM1805982","n":"Under The Moon-light 우린 나란히 앉아","a":[{"i":"4GAVUIrGNz35VbCFfHTsca","n":"saevom"},{"i":"1xmvq3HHYYVMuxyhjqMGBo","n":"Jung Soan"},{"i":"4SXIrAFg5kNHCjflnHh34c","n":"Byun Heungsoo"}],"p":14,"r":"2018-07-29","l":"unsvrecords","im":"https://i.scdn.co/image/ab67616d0000b2732d65290a61367f9e35cfd5ff","ps":[{"i":"37i9dQZF1DWZYjbSZYSpu6","n":11,"a":1614650424000,"p":489},{"i":"37i9dQZF1DXdTb8AG95jne","n":44,"a":1614650283000,"p":335},{"i":"37i9dQZF1DX71SU2C3nX8z","n":62,"a":1614652486000,"p":243}],"pp":1067},"im1811737":{"i":"4hSypX5zH1OUW0BDQZuAQV","is":"KRMIM1811737","n":"Sweet Fuss","a":[{"i":"6HbvERy3ULYCot6g8Sp2ol","n":"zai.ro"},{"i":"3CHn74oCO6xiThDGQcDMeA","n":"Kim MinSeok"}],"p":38,"r":"2018-11-05","l":"Genie Music Corporation, Stone Music Entertainment","im":"https://i.scdn.co/image/ab67616d0000b27325a10c7ae8c60c3875723ab4","ps":[{"i":"37i9dQZF1DXbirtHQBuwCo","n":48,"a":1614649565000,"p":458}],"pp":458},"im1808418":{"i":"0Ilpk65GBe1sO2KbrzNqZH","is":"KRMIM1808418","n":"Sunflower","a":[{"i":"3VQDqjQ4wJyw8PzpGdlZpB","n":"Colde"}],"p":42,"r":"2018-09-13","l":"WAVY | PASSPORT SEOUL","im":"https://i.scdn.co/image/ab67616d0000b27395883170734b622d2312fa64","ps":[{"i":"37i9dQZF1DXbirtHQBuwCo","n":49,"a":1614649565000,"p":453}],"pp":453},"im1805200":{"i":"5xfXE4spp0GEniQYqUmjjT","is":"KRMIM1805200","n":"Nighty Night","a":[{"i":"3uo7KLyxuiANGmwDocxMnw","n":"Nieah"}],"p":32,"r":"2018-07-23","l":"Stone Music Entertainment","im":"https://i.scdn.co/image/ab67616d0000b273660c1d43312ca92a3a0fa16c","ps":[{"i":"37i9dQZF1DXbirtHQBuwCo","n":51,"a":1614649565000,"p":444}],"pp":444},"im1804896":{"i":"6hyzfmjGcZlsGBJT7VrLMv","is":"KRMIM1804896","n":"Tats","a":[{"i":"6njP39Dygk8WBwc7gR8Q48","n":"BADROOM"}],"p":10,"r":"2018-07-12","l":"BADMOON ENT","im":"https://i.scdn.co/image/ab67616d0000b2732bc1d4d1d511ac462ccd266c","ps":[{"i":"37i9dQZF1DXbirtHQBuwCo","n":66,"a":1614649565000,"p":382}],"pp":382},"im1808666":{"i":"0CEqskv809IL2G2lCJKulP","is":"KRMIM1808666","n":"Kiss 키스","a":[{"i":"08J6v4qHZz06ua0qAicWmE","n":"Kim Sawol"}],"p":4,"r":"2018-09-16","l":"Kim Sawol","im":"https://i.scdn.co/image/ab67616d0000b27345a5d0cfc656f2c5412257c2","ps":[{"i":"37i9dQZF1DX71SU2C3nX8z","n":19,"a":1614652486000,"p":374}],"pp":374},"im1806832":{"i":"7rRHe9b5NZzx78TG6BMYWH","is":"KRMIM1806832","n":"Night Air 밤은 우릴","a":[{"i":"4GAVUIrGNz35VbCFfHTsca","n":"saevom"},{"i":"0Mx0eyyqDGAN2VFvzuSOtR","n":"Yoon Hansol"}],"p":2,"r":"2018-08-12","l":"unsvrecords","im":"https://i.scdn.co/image/ab67616d0000b2737a511fe3b9c2229222cc6af3","ps":[{"i":"37i9dQZF1DX71SU2C3nX8z","n":25,"a":1614652486000,"p":352}],"pp":352},"im1810873":{"i":"5zrGyOSamPVtvvrBx62swW","is":"KRMIM1810873","n":"안개 fog","a":[{"i":"6aQtLvZBb5B8fy6KfWRvTQ","n":"HERD"}],"p":6,"r":"2018-11-26","l":"HERD","im":"https://i.scdn.co/image/ab67616d0000b2738f0d951140a5f6da32981681","ps":[{"i":"37i9dQZF1DX71SU2C3nX8z","n":33,"a":1614652486000,"p":325}],"pp":325},"im1812823":{"i":"0GSpRWqXlHVkhooCehKHRM","is":"KRMIM1812823","n":"Learn to love 그대가 내 안에 박혔다","a":[{"i":"689wBe4v9rvHjdNB4JUgYq","n":"Hwang Chi Yeul"}],"p":14,"r":"2018-11-20","l":"하우엔터테인먼트","im":"https://i.scdn.co/image/ab67616d0000b2733f1e6d72bf47506a69d03375","ps":[{"i":"37i9dQZF1DX71SU2C3nX8z","n":45,"a":1614652486000,"p":288}],"pp":288},"im1810061":{"i":"3SWfB6TxnJI59plsx11FSf","is":"KRMIM1810061","n":"Someone’s Shining 누군가의 빛나던 - Album Ver.","a":[{"i":"6AtePm872YnH0PPQZpNFry","n":"WISUE"}],"p":17,"r":"2018-10-13","l":"Acoustie Music","im":"https://i.scdn.co/image/ab67616d0000b2734463ae4f7c1d062eba59c988","ps":[{"i":"37i9dQZF1DX71SU2C3nX8z","n":57,"a":1614652486000,"p":255}],"pp":255},"im1801266":{"i":"2UwNBWxyoIOVsXuf8xgfRO","is":"KRMIM1801266","n":"Love Gamble","a":[{"i":"7vwvEhbpyzAU0I5uqx3nwg","n":"Deletis"},{"i":"7yOasijEMzKW0xiBhOVoYu","n":"Sayah"}],"p":2,"r":"2018-05-21","l":"그래비티뮤직","im":"https://i.scdn.co/image/ab67616d0000b27301adc17a22810c9a0c4820d3","ps":[{"i":"37i9dQZF1DWZYjbSZYSpu6","n":24,"a":1614650424000,"p":429}],"pp":429}},"s":["im2","im19"]}