{"d":{"234":{"i":"3ugCSRkkewHctDELil9Ixq","is":"USUM71925234","n":"Slow Down - Acoustic","a":[{"i":"4ryoUS0W8qXokfMxrlJt6O","n":"Skip Marley"},{"i":"3Y7RZ31TRPVadSFVy1o8os","n":"H.E.R."}],"p":48,"r":"2020-01-17","l":"Island Records","im":"https://i.scdn.co/image/ab67616d0000b27330c7dbcff8778847ad08c0a3","ps":[{"i":"37i9dQZF1DXaXDsfv6nvZ5","n":48,"a":1614613663000,"p":488}],"pp":488},"250":{"i":"11wzBoHOY1WJmIPQVBavGe","is":"USUM71925250","n":"Winona Ryder","a":[{"i":"7jLSEPYCYQ5ssWU3BICqrW","n":"Picture This"}],"p":55,"r":"2020-01-10","l":"Republic Records","im":"https://i.scdn.co/image/ab67616d0000b273952e27c71894ff7194e1e65d","ps":[{"i":"37i9dQZF1DX0JRPg4lEmCd","n":25,"a":1613617320000,"p":73}],"pp":73},"398":{"i":"5RoLPWq3JJyeeGl94We2YQ","is":"USUM71925398","n":"Till We Fall In Love","a":[{"i":"6kLN4GaYwfWUe0A4cnNS6d","n":"dEVOLVE"},{"i":"17rnpuu2LApoCL4x8fObZg","n":"Alx Veliz"},{"i":"5sK8BsvyDl4TFA6KaBf8or","n":"Charly Black"}],"p":0,"r":"2020-01-10","l":"Casablanca Records (Republic Records)","im":"https://i.scdn.co/image/ab67616d0000b273a2be458c682ceeb3795a5522","ps":[{"i":"37i9dQZF1DX6uIc2aogDNQ","n":56,"a":1614568493000,"p":138}],"pp":138},"497":{"i":"2LOOPj4zQakUeNy1gIcynX","is":"USUM71925497","n":"Me Dediqué A Perderte","a":[{"i":"6JBGaRYIWS7fzKP0qGgZve","n":"Crecer German"}],"p":60,"r":"2020-01-17","l":"UMLE - Fonovisa","im":"https://i.scdn.co/image/ab67616d0000b273312179a61cd9b30e9204d666","ps":[{"i":"37i9dQZF1DX37tvjlT1GSK","n":23,"a":1614362444000,"p":603}],"pp":603},"528":{"i":"3IcMPtimQDr9w4kE9p0Lcs","is":"USUM71925528","n":"Rocketship","a":[{"i":"12Zk1DFhCbHY6v3xep2ZjI","n":"070 Shake"}],"p":0,"r":"2020-01-17","l":"Getting Out Our Dreams Inc. (G.O.O.D.) Music / IDJ","im":"https://i.scdn.co/image/ab67616d0000b273389135ed5e7d6bcc879dd39e","ps":[{"i":"37i9dQZF1DWSklq431ca03","n":76,"a":1613759847000,"p":22}],"pp":22},"532":{"i":"4I4smJ6xLCaLQmNYUTQg9R","is":"USUM71925532","n":"A Qué Sabe El Olvido","a":[{"i":"6sq1yF0OZEWA4xoXVKW1L9","n":"Alejandro Fernández"}],"p":57,"r":"2020-02-14","l":"UMLE - Latino","im":"https://i.scdn.co/image/ab67616d0000b273521fbe6ad41ca318f6e5dbb9","ps":[{"i":"37i9dQZF1DX5b2iE2KAwwS","n":19,"a":1613109660000,"p":151},{"i":"37i9dQZF1DWUCW9VX8yNjX","n":54,"a":1613098217000,"p":102},{"i":"37i9dQZF1DWVvGpUc6O5W1","n":16,"a":1613147020000,"p":79}],"pp":332},"533":{"i":"6Ecm8kb3fP58vsFs252AUR","is":"USUM71925533","n":"Decepciones","a":[{"i":"6sq1yF0OZEWA4xoXVKW1L9","n":"Alejandro Fernández"}],"p":55,"r":"2020-02-14","l":"UMLE - Latino","im":"https://i.scdn.co/image/ab67616d0000b273521fbe6ad41ca318f6e5dbb9","ps":[{"i":"37i9dQZF1DWUCW9VX8yNjX","n":11,"a":1613098217000,"p":157}],"pp":157},"534":{"i":"68teZcAANkNhea13y7GqDP","is":"USUM71925534","n":"Más No Puedo","a":[{"i":"6sq1yF0OZEWA4xoXVKW1L9","n":"Alejandro Fernández"},{"i":"0XwVARXT135rw8lyw1EeWP","n":"Christian Nodal"}],"p":63,"r":"2020-02-14","l":"UMLE - Latino","im":"https://i.scdn.co/image/ab67616d0000b273521fbe6ad41ca318f6e5dbb9","ps":[{"i":"37i9dQZF1DWUCW9VX8yNjX","n":8,"a":1613098217000,"p":162},{"i":"37i9dQZF1DX7VikJCuOpfO","n":55,"a":1614110915000,"p":124}],"pp":286},"535":{"i":"5QtzrMvhtEUQzCkehNQqdh","is":"USUM71925535","n":"Mudanza A La Luna","a":[{"i":"6sq1yF0OZEWA4xoXVKW1L9","n":"Alejandro Fernández"}],"p":53,"r":"2020-02-14","l":"UMLE - Latino","im":"https://i.scdn.co/image/ab67616d0000b273521fbe6ad41ca318f6e5dbb9","ps":[{"i":"37i9dQZF1DWUCW9VX8yNjX","n":9,"a":1613098217000,"p":160}],"pp":160},"536":{"i":"2Uv19wAiksXZcFM84R00KQ","is":"USUM71925536","n":"Por Tu Adiós","a":[{"i":"6sq1yF0OZEWA4xoXVKW1L9","n":"Alejandro Fernández"}],"p":53,"r":"2020-02-14","l":"UMLE - Latino","im":"https://i.scdn.co/image/ab67616d0000b273521fbe6ad41ca318f6e5dbb9","ps":[{"i":"37i9dQZF1DWUCW9VX8yNjX","n":14,"a":1613098217000,"p":152}],"pp":152},"537":{"i":"1LBMyEhRDTzwvZPqaGvnCJ","is":"USUM71925537","n":"Mentí","a":[{"i":"6sq1yF0OZEWA4xoXVKW1L9","n":"Alejandro Fernández"},{"i":"4PPoI9LuYeFX8V674Z1R6l","n":"Vicente Fernández"}],"p":57,"r":"2020-02-14","l":"UMLE - Latino","im":"https://i.scdn.co/image/ab67616d0000b273521fbe6ad41ca318f6e5dbb9","ps":[{"i":"37i9dQZF1DX7VikJCuOpfO","n":15,"a":1614110915000,"p":185},{"i":"37i9dQZF1DWUCW9VX8yNjX","n":7,"a":1613098217000,"p":163}],"pp":348},"538":{"i":"1dsIlMbsQao9WntC9SrwvO","is":"USUM71925538","n":"La Mesa 20","a":[{"i":"6sq1yF0OZEWA4xoXVKW1L9","n":"Alejandro Fernández"}],"p":52,"r":"2020-02-14","l":"UMLE - Latino","im":"https://i.scdn.co/image/ab67616d0000b273521fbe6ad41ca318f6e5dbb9","ps":[{"i":"37i9dQZF1DWUCW9VX8yNjX","n":1,"a":1613098217000,"p":173}],"pp":173},"539":{"i":"1Mg9TGZPjLc9CCV2PonaO8","is":"USUM71925539","n":"Hasta En Mis Huesos","a":[{"i":"6sq1yF0OZEWA4xoXVKW1L9","n":"Alejandro Fernández"}],"p":52,"r":"2020-02-14","l":"UMLE - Latino","im":"https://i.scdn.co/image/ab67616d0000b273521fbe6ad41ca318f6e5dbb9","ps":[{"i":"37i9dQZF1DWUCW9VX8yNjX","n":13,"a":1613098217000,"p":154}],"pp":154},"540":{"i":"6UnKIvdbaPzCpHnceW372Y","is":"USUM71925540","n":"Nuestro Gran Secreto","a":[{"i":"6sq1yF0OZEWA4xoXVKW1L9","n":"Alejandro Fernández"}],"p":52,"r":"2020-02-14","l":"UMLE - Latino","im":"https://i.scdn.co/image/ab67616d0000b273521fbe6ad41ca318f6e5dbb9","ps":[{"i":"37i9dQZF1DWUCW9VX8yNjX","n":39,"a":1613098217000,"p":118}],"pp":118},"571":{"i":"7JGUQpRKKQf1CfZFBVYPxi","is":"USUM71925571","n":"A Vapor","a":[{"i":"51XrH5fQP2oIQynuKxSWcW","n":"Sky Rompiendo"},{"i":"0EFisYRi20PTADoJrifHrz","n":"Jhay Cortez"},{"i":"40lro6xpFS9TxV2uC7yvs4","n":"Leebrian"},{"i":"0Q8NcsJwoCbZOHHW63su5S","n":"Mora"}],"p":57,"r":"2020-01-17","l":"UMLE - Latino","im":"https://i.scdn.co/image/ab67616d0000b2737d659926553c8b5ba02444ee","ps":[{"i":"37i9dQZF1DX29qo6meCGNU","n":63,"a":1614364159000,"p":239},{"i":"37i9dQZF1DX56TFraF4fNu","n":48,"a":1614278132000,"p":97}],"pp":336},"577":{"i":"26KjVtX8XoJ4XFP5On8T1o","is":"USUM71925577","n":"El Último Baile (Mia 5)","a":[{"i":"5J7rXWjtn5HzUkJ4Jet8Fr","n":"Alvaro Diaz"},{"i":"51aWHhJ7AjxKmZ4dDUc0sm","n":"Kablito"}],"p":48,"r":"2020-01-31","l":"Int'l Latin America","im":"https://i.scdn.co/image/ab67616d0000b27374d62f9a88da68519fa864f4","ps":[{"i":"37i9dQZF1DWVG6tTakNOen","n":22,"a":1614294060000,"p":22}],"pp":22},"578":{"i":"03V0FZwKTJhXeW2zVNkyP7","is":"USUM71925578","n":"Reina Pepiada","a":[{"i":"5J7rXWjtn5HzUkJ4Jet8Fr","n":"Alvaro Diaz"}],"p":54,"r":"2020-01-31","l":"Int'l Latin America","im":"https://i.scdn.co/image/ab67616d0000b27374d62f9a88da68519fa864f4","ps":[{"i":"37i9dQZF1DX4Ghyz32wen4","n":48,"a":1614654969000,"p":28},{"i":"37i9dQZF1DWVG6tTakNOen","n":17,"a":1614294060000,"p":23}],"pp":51},"579":{"i":"48fSe5XXSej9Gc0L9QlNGN","is":"USUM71925579","n":"No Te Quiero Perder","a":[{"i":"5J7rXWjtn5HzUkJ4Jet8Fr","n":"Alvaro Diaz"}],"p":48,"r":"2020-01-31","l":"Int'l Latin America","im":"https://i.scdn.co/image/ab67616d0000b27374d62f9a88da68519fa864f4","ps":[{"i":"37i9dQZF1DWXYWuNDAdJsw","n":45,"a":1612804632000,"p":525},{"i":"37i9dQZF1DWVG6tTakNOen","n":5,"a":1614294060000,"p":26}],"pp":551},"619":{"i":"7GCVboEDzfL3NKp1NrAgHR","is":"USUM71925619","n":"Wrong Direction","a":[{"i":"5p7f24Rk5HkUZsaS3BLG5F","n":"Hailee Steinfeld"}],"p":5,"r":"2020-01-01","l":"Republic Records","im":"https://i.scdn.co/image/ab67616d0000b273727a9a47d93397148f754451","ps":[{"i":"37i9dQZF1DX1ngEVM0lKrb","n":59,"a":1614689187000,"p":431},{"i":"37i9dQZF1DXd96qtxaNwhT","n":62,"a":1613653200000,"p":206},{"i":"37i9dQZF1DXdwamLwUeMED","n":25,"a":1613084400000,"p":111}],"pp":748},"641":{"i":"5F26nsU7gR1vnjRwvr9lif","is":"USUM71925641","n":"Hands Off Me","a":[{"i":"2YqJwmohaNjg9lg51flSax","n":"Chiiild"}],"p":0,"r":"2020-01-22","l":"Avant Garden","im":"https://i.scdn.co/image/ab67616d0000b2730c9d2a5027ce256df34e6a64","ps":[{"i":"37i9dQZF1DWSfMe9z89s9B","n":78,"a":1614441550000,"p":453}],"pp":453},"662":{"i":"5BfvUt5ztFuAyhWjgWzjr1","is":"USUM71925662","n":"Pirouette","a":[{"i":"2YqJwmohaNjg9lg51flSax","n":"Chiiild"}],"p":57,"r":"2020-02-28","l":"Avant Garden","im":"https://i.scdn.co/image/ab67616d0000b2730b891ecf0990dac512caf82f","ps":[{"i":"37i9dQZF1DWXMg4uP5o3dm","n":79,"a":1597685590000,"p":266},{"i":"37i9dQZF1DX1F430ihQKsD","n":78,"a":1614374621000,"p":126}],"pp":392},"697":{"i":"1CdlRy7UMR7Oz8pnUFFX2G","is":"USUM71925697","n":"Oh Yes (feat. Marvin Gaye & Tammi Terrell)","a":[{"i":"5ECHe2MSGF8z12B7wv08x5","n":"Paris Green"},{"i":"3koiLjNrgRTNbOwViDipeA","n":"Marvin Gaye"},{"i":"75jNCko3SnEMI5gwGqrbb8","n":"Tammi Terrell"}],"p":43,"r":"2020-07-17","l":"Positiva / Astralwerks / Motown Records","im":"https://i.scdn.co/image/ab67616d0000b2735873884696b33b0ab343fb69","ps":[{"i":"37i9dQZF1DX2CXe9Z4UDn7","n":48,"a":1614294000000,"p":27}],"pp":27},"096":{"i":"4QtQgsK7DChmU4EM5NtqyK","is":"USUM71925096","n":"Borracho De Amor","a":[{"i":"5DUlefCLzVRzNWaNURTFpK","n":"Cali Y El Dandee"},{"i":"0vR2qb8m9WHeZ5ByCbimq2","n":"Reik"}],"p":60,"r":"2020-01-24","l":"Cali y El Dandee PS","im":"https://i.scdn.co/image/ab67616d0000b2739b8ee7b8f1a790ba304e483e","ps":[{"i":"37i9dQZF1DXdnGF35OawbN","n":54,"a":1613576127000,"p":1143},{"i":"37i9dQZF1DX4nV8QNjO7nb","n":33,"a":1613521003000,"p":752},{"i":"37i9dQZF1DX9vJ2U3sN7xj","n":68,"a":1613753005000,"p":480},{"i":"37i9dQZF1DXdOe3IHMQPm8","n":47,"a":1614315660000,"p":184},{"i":"37i9dQZF1DWUzaE9UzQeCb","n":51,"a":1611341333000,"p":165},{"i":"37i9dQZF1DXc0kiEm1shcT","n":72,"a":1614007820000,"p":56}],"pp":2780}},"s":[]}